ig/__init__.py
ig/cli.py
godl-0.1.6.dist-info/METADATA
godl-0.1.6.dist-info/WHEEL
godl-0.1.6.dist-info/entry_points.txt
godl-0.1.6.dist-info/top_level.txt
godl-0.1.6.dist-info/RECORD
